LICENSE
MANIFEST.in
README.md
pyproject.toml
setup.py
pyyjson/__init__.py
pyyjson/__init__.pyi
pyyjson/binding.c
pyyjson/memory.c
pyyjson/memory.h
pyyjson/serde.h
pyyjson/wrapper.py
pyyjson/yyjson.c
pyyjson/yyjson.h
pyyjson.egg-info/PKG-INFO
pyyjson.egg-info/SOURCES.txt
pyyjson.egg-info/dependency_links.txt
pyyjson.egg-info/top_level.txt
tests/test_basic.py