Metadata-Version: 2.1
Name: pyyjson
Version: 0.2.0
Summary: yet another json libs using yyjson
Author-email: Hyunsung Lee <ita9naiwa@gmail.com>
License: MIT
Classifier: Programming Language :: Python :: 3
Classifier: License :: OSI Approved :: MIT License
Requires-Python: >=3.3
License-File: LICENSE
